hellopymsdl/__init__.py
hellopymsdl/__main__.py
hellopymsdl/service/MessageService.py
hellopymsdl/service/__init__.py
hellopymsdl_rsrc/__init__.py
hellopymsdl_rsrc/message.txt
hellopymsdl-3.0.1.dist-info/LICENSE
hellopymsdl-3.0.1.dist-info/METADATA
hellopymsdl-3.0.1.dist-info/WHEEL
hellopymsdl-3.0.1.dist-info/entry_points.txt
hellopymsdl-3.0.1.dist-info/RECORD
