Metadata-Version: 2.1
Name: hellopymsdl
Version: 3.0.1
Summary: A Python template inspired from the Maven Standard Directory Layout
Home-page: https://github.com/dev4py/pymsdl_template
License: Apache-2.0
Keywords: peotry,maven,standard,directory,layout
Author: author
Author-email: author@mail.com
Requires-Python: >=3.11,<4.0
Classifier: Intended Audience :: Developers
Classifier: License :: OSI Approved :: Apache Software License
Classifier: Programming Language :: Python
Classifier: Programming Language :: Python :: 3
Classifier: Programming Language :: Python :: 3.11
Classifier: Programming Language :: Python :: 3.12
Classifier: Topic :: Software Development :: Build Tools
Project-URL: Documentation, https://github.com/dev4py/pymsdl_template/blob/main/README.md
Project-URL: Repository, https://github.com/dev4py/pymsdl_template
